ansys/api/systemcoupling/VERSION
ansys/api/systemcoupling/__init__.py
ansys/api/systemcoupling/py.typed
ansys/api/systemcoupling/v0/command.proto
ansys/api/systemcoupling/v0/command_pb2.py
ansys/api/systemcoupling/v0/command_pb2.pyi
ansys/api/systemcoupling/v0/command_pb2_grpc.py
ansys/api/systemcoupling/v0/command_pb2_grpc.pyi
ansys/api/systemcoupling/v0/error.proto
ansys/api/systemcoupling/v0/error_pb2.py
ansys/api/systemcoupling/v0/error_pb2.pyi
ansys/api/systemcoupling/v0/error_pb2_grpc.py
ansys/api/systemcoupling/v0/error_pb2_grpc.pyi
ansys/api/systemcoupling/v0/output_stream.proto
ansys/api/systemcoupling/v0/output_stream_pb2.py
ansys/api/systemcoupling/v0/output_stream_pb2.pyi
ansys/api/systemcoupling/v0/output_stream_pb2_grpc.py
ansys/api/systemcoupling/v0/output_stream_pb2_grpc.pyi
ansys/api/systemcoupling/v0/process.proto
ansys/api/systemcoupling/v0/process_pb2.py
ansys/api/systemcoupling/v0/process_pb2.pyi
ansys/api/systemcoupling/v0/process_pb2_grpc.py
ansys/api/systemcoupling/v0/process_pb2_grpc.pyi
ansys/api/systemcoupling/v0/solution.proto
ansys/api/systemcoupling/v0/solution_pb2.py
ansys/api/systemcoupling/v0/solution_pb2.pyi
ansys/api/systemcoupling/v0/solution_pb2_grpc.py
ansys/api/systemcoupling/v0/solution_pb2_grpc.pyi
ansys/api/systemcoupling/v0/variant.proto
ansys/api/systemcoupling/v0/variant_pb2.py
ansys/api/systemcoupling/v0/variant_pb2.pyi
ansys/api/systemcoupling/v0/variant_pb2_grpc.py
ansys/api/systemcoupling/v0/variant_pb2_grpc.pyi
ansys_api_systemcoupling-0.2.0.dist-info/LICENSE
ansys_api_systemcoupling-0.2.0.dist-info/METADATA
ansys_api_systemcoupling-0.2.0.dist-info/WHEEL
ansys_api_systemcoupling-0.2.0.dist-info/entry_points.txt
ansys_api_systemcoupling-0.2.0.dist-info/top_level.txt
ansys_api_systemcoupling-0.2.0.dist-info/RECORD
