Metadata-Version: 2.1
Name: ansys-api-systemcoupling
Version: 0.2.0
Summary: Autogenerated python gRPC interface package for ansys-api-systemcoupling, built on 15:37:55 on 09 July 2024
Home-page: https://github.com/ansys/ansys-api-systemcoupling
Author: ANSYS, Inc.
Author-email: support@ansys.com
License: MIT
Requires-Python: >=3.7
License-File: LICENSE
Requires-Dist: grpcio ~=1.30
Requires-Dist: protobuf <5,>=3.19
